MANIFEST.in
README.rst
setup.py
vpgtools/__init__.py
vpgtools.egg-info/PKG-INFO
vpgtools.egg-info/SOURCES.txt
vpgtools.egg-info/dependency_links.txt
vpgtools.egg-info/not-zip-safe
vpgtools.egg-info/requires.txt
vpgtools.egg-info/top_level.txt