Metadata-Version: 1.0
Name: vpgtools
Version: 0.1
Summary: Computer vision tools for the study of politics
Home-page: https://github.com/CasAndreu/vpgtools
Author: Andreu Casas
Author-email: andreucasas@nyu.edu
License: MIT
Platform: UNKNOWN
